neuromeka/__init__.py
neuromeka/ecat.py
neuromeka/enums.py
neuromeka/eye.py
neuromeka/indydcp2.py
neuromeka/indydcp3.py
neuromeka/moby.py
neuromeka/motor.py
neuromeka/common/Converting_Manager.py
neuromeka/common/__init__.py
neuromeka/common/jsmin.py
neuromeka/common/program_converter.py
neuromeka/common/record_plot.py
neuromeka/common/utils.py
neuromeka/proto/__init__.py
neuromeka/proto/boot_msgs_pb2.py
neuromeka/proto/boot_msgs_pb2_grpc.py
neuromeka/proto/boot_pb2.py
neuromeka/proto/boot_pb2_grpc.py
neuromeka/proto/common_msgs_pb2.py
neuromeka/proto/common_msgs_pb2_grpc.py
neuromeka/proto/config_msgs_pb2.py
neuromeka/proto/config_msgs_pb2_grpc.py
neuromeka/proto/config_pb2.py
neuromeka/proto/config_pb2_grpc.py
neuromeka/proto/control_msgs_pb2.py
neuromeka/proto/control_msgs_pb2_grpc.py
neuromeka/proto/control_pb2.py
neuromeka/proto/control_pb2_grpc.py
neuromeka/proto/cri_msgs_pb2.py
neuromeka/proto/cri_msgs_pb2_grpc.py
neuromeka/proto/cri_pb2.py
neuromeka/proto/cri_pb2_grpc.py
neuromeka/proto/device_msgs_pb2.py
neuromeka/proto/device_msgs_pb2_grpc.py
neuromeka/proto/device_pb2.py
neuromeka/proto/device_pb2_grpc.py
neuromeka/proto/ethercat_msgs_pb2.py
neuromeka/proto/ethercat_msgs_pb2_grpc.py
neuromeka/proto/ethercat_pb2.py
neuromeka/proto/ethercat_pb2_grpc.py
neuromeka/proto/eyetask_pb2.py
neuromeka/proto/eyetask_pb2_grpc.py
neuromeka/proto/indyeye_pb2.py
neuromeka/proto/indyeye_pb2_grpc.py
neuromeka/proto/linear_pb2.py
neuromeka/proto/linear_pb2_grpc.py
neuromeka/proto/moby_msgs_pb2.py
neuromeka/proto/moby_msgs_pb2_grpc.py
neuromeka/proto/moby_pb2.py
neuromeka/proto/moby_pb2_grpc.py
neuromeka/proto/plotting_pb2.py
neuromeka/proto/plotting_pb2_grpc.py
neuromeka/proto/rtde_msgs_pb2.py
neuromeka/proto/rtde_msgs_pb2_grpc.py
neuromeka/proto/rtde_pb2.py
neuromeka/proto/rtde_pb2_grpc.py
neuromeka/proto/teleop_dev_pb2.py
neuromeka/proto/teleop_dev_pb2_grpc.py
neuromeka/proto_step/__init__.py
neuromeka/proto_step/boot_msgs_pb2.py
neuromeka-3.4.0.4.dist-info/METADATA
neuromeka-3.4.0.4.dist-info/WHEEL
neuromeka-3.4.0.4.dist-info/top_level.txt
neuromeka-3.4.0.4.dist-info/RECORD
