Metadata-Version: 2.4
Name: neuromeka
Version: 3.4.0.4
Summary: Neuromeka client protocols for IndyDCP3, IndyEye, Moby, Ecat, and Motor
Home-page: https://github.com/neuromeka-robotics/neuromeka-package
Author: Neuromeka
Author-email: technical-support@neuromeka.com
Classifier: Development Status :: 3 - Alpha
Classifier: Intended Audience :: Developers
Classifier: License :: OSI Approved :: MIT License
Classifier: Operating System :: OS Independent
Classifier: Programming Language :: Python :: 3.7
Classifier: Programming Language :: Python :: 3.8
Classifier: Programming Language :: Python :: 3.9
Classifier: Programming Language :: Python :: 3.10
Classifier: Programming Language :: Python :: 3.11
Classifier: Programming Language :: Python :: 3.12
Requires-Python: >=3.7
Requires-Dist: grpcio<=1.39.0,>=1.34.1; python_version < "3.9"
Requires-Dist: grpcio-tools<=1.39.0,>=1.34.1; python_version < "3.9"
Requires-Dist: protobuf==3.17.3; python_version < "3.9"
Requires-Dist: requests==2.22.0; python_version < "3.9"
Requires-Dist: Pillow<=9.5.0,>=8.4.0; python_version < "3.9"
Requires-Dist: numpy<=1.21.6,>=1.19.4; python_version < "3.9"
Requires-Dist: pyModbusTCP==0.2.1; python_version < "3.9"
Requires-Dist: netifaces==0.11.0; python_version < "3.9"
Requires-Dist: grpcio==1.59.0; python_version >= "3.9"
Requires-Dist: grpcio-tools==1.59.0; python_version >= "3.9"
Requires-Dist: protobuf<=4.25.4,>=4.24.4; python_version >= "3.9"
Requires-Dist: requests<=2.32.0,>=2.31.0; python_version >= "3.9"
Requires-Dist: urllib3<=2.2.2,>=2.0.7; python_version >= "3.9"
Requires-Dist: Pillow==9.5.0; python_version >= "3.9"
Requires-Dist: numpy<=1.26.4,>=1.21.6; python_version >= "3.9"
Requires-Dist: pyModbusTCP==0.2.1; python_version >= "3.9"
Requires-Dist: netifaces2; python_version >= "3.9"
Dynamic: author
Dynamic: author-email
Dynamic: classifier
Dynamic: description
Dynamic: description-content-type
Dynamic: home-page
Dynamic: provides-extra
Dynamic: requires-python
Dynamic: summary
